[
  {
    "key": "dabang::57168701",
    "id": "57168701",
    "source": "dabang",
    "data": {
      "source": "dabang",
      "id": "57168701",
      "url": "https://www.dabangapp.com/room/6a0ebf036792597ec6762d29",
      "agency": "런공인중개사사무소",
      "phone": "031-213-5888",
      "region": "경기도 수원시 영통구 원천동",
      "address": "경기도 수원시 영통구 원천동 576",
      "lat": 37.2778717716,
      "lon": 127.0498744349,
      "title": "8선착순 아주대병원 옆 오피스텔같은 깔끔한 풀옵션 원룸8",
      "deposit": 1000,
      "rent": 50,
      "maint": 10,
      "total": 60,
      "type": "원룸",
      "area": "19.83",
      "floor": "5층/5층",
      "img1": "https://d1774jszgerdmk.cloudfront.net/1024/Kka4iP6Wo7jW5QoE2Tnb_",
      "img2": "https://d1774jszgerdmk.cloudfront.net/1024/grFuGDXoqtJMXojLU43XH"
    },
    "savedAt": "2026-05-22T11:24:35.028Z",
    "rating": {
      "noise": 2,
      "mold": 2,
      "security": 4,
      "pests": 3
    },
    "notes": "dgdg"
  },
  {
    "key": "dabang::57127522",
    "id": "57127522",
    "source": "dabang",
    "data": {
      "source": "dabang",
      "id": "57127522",
      "url": "https://www.dabangapp.com/room/6a0bccc5d8b03b7fe7d065ec",
      "agency": "모아공인중개사사무소",
      "phone": "031-895-6170",
      "region": "경기도 수원시 영통구 원천동",
      "address": "경기도 수원시 영통구 원천동 576",
      "lat": 37.2778717716,
      "lon": 127.0498744349,
      "title": "MOAㅣ즉시입주Oㅣ깔끔선호Oㅣ아주대Oㅣ풀옵션O",
      "deposit": 1000,
      "rent": 50,
      "maint": 10,
      "total": 60,
      "type": "원룸",
      "area": "19.83",
      "floor": "5층/5층",
      "img1": "https://d1774jszgerdmk.cloudfront.net/1024/VsA68Mdo0JddQVrepx5Zw",
      "img2": "https://d1774jszgerdmk.cloudfront.net/1024/juj1vRm23LcF0-nXkI8WP"
    },
    "savedAt": "2026-05-22T11:24:36.811Z",
    "rating": null,
    "notes": ""
  },
  {
    "key": "dabang::57186363",
    "id": "57186363",
    "source": "dabang",
    "data": {
      "source": "dabang",
      "id": "57186363",
      "url": "https://www.dabangapp.com/room/6a100b3eb1de7a478b6dd928",
      "agency": "광교파트너공인중개사사무소",
      "phone": "031-211-0070",
      "region": "경기도 수원시 영통구 원천동",
      "address": "경기도 수원시 영통구 원천동 576-1",
      "lat": 37.2776844368873,
      "lon": 127.049680370728,
      "title": "아주대병원 옆 광교택지지구내 깔끔한 풀옵션 원룸",
      "deposit": 1000,
      "rent": 53,
      "maint": 15,
      "total": 68,
      "type": "원룸",
      "area": "20",
      "floor": "4층/5층",
      "img1": "https://d1774jszgerdmk.cloudfront.net/1024/jDsJI6ByJya3pM4_80tSG",
      "img2": "https://d1774jszgerdmk.cloudfront.net/1024/0Xfqk6Rl1B8A4TaXb64Am"
    },
    "savedAt": "2026-05-22T11:24:37.404Z",
    "rating": null,
    "notes": ""
  }
]